dch/__init__.py
dch/cog.py
discord_custom_help-0.0.7.dist-info/LICENSE
discord_custom_help-0.0.7.dist-info/METADATA
discord_custom_help-0.0.7.dist-info/WHEEL
discord_custom_help-0.0.7.dist-info/top_level.txt
discord_custom_help-0.0.7.dist-info/RECORD
